cLogAnalysis/__init__.py
cLogAnalysis/cLogAnalysis.py
cLogAnalysis-0.0.3.dist-info/LICENSE
cLogAnalysis-0.0.3.dist-info/METADATA
cLogAnalysis-0.0.3.dist-info/WHEEL
cLogAnalysis-0.0.3.dist-info/top_level.txt
cLogAnalysis-0.0.3.dist-info/RECORD
